[
    {
        "id": 1,
        "title": "Children’s Jakarta Hoops Fest",
        "description": "Come and knock on our door. We've been waiting for you. Where the kisses...",
        "image": "https://demo2.themewarrior.com/hospitalplus/wp-content/uploads/sites/22/2015/02/gallery-1-280x215.jpg"
    },
    {
        "id": 2,
        "title": "There’s something special about...",
        "description": "Our whole universe was in a hot dense state, then nearly fourteen billion years...",
        "image": "https://demo2.themewarrior.com/hospitalplus/wp-content/uploads/sites/22/2015/01/news-11-280x215.jpg"
    },
    {
        "id": 3,
        "title": "Staying Healthy As You...",
        "description": "This is it, this is it. This is life, the one you get, so...",
        "image": "https://demo2.themewarrior.com/hospitalplus/wp-content/uploads/sites/22/2016/04/Important-Old-Care-280x215.jpg"
    },
    {
        "id": 4,
        "title": "Happiest Baby on the...",
        "description": "Since the dawn of time, there has been a process to developing web you...",
        "image": "https://demo2.themewarrior.com/hospitalplus/wp-content/uploads/sites/22/2016/04/Check-your-Baby-280x215.jpg"
    },
    {
        "id": 5,
        "title": "Parenting Workshop",
        "description": "Join the Desert Sun Guild for a fun evening benefiting care and Seattle Children’s...",
        "image": "https://demo2.themewarrior.com/hospitalplus/wp-content/uploads/sites/22/2016/04/Parenting-Workshop-280x215.jpg"
    },
    {
        "id": 6,
        "title": "Fresh goes better in...",
        "description": "You take the good, you take the bad, you take them both and there...",
        "image": "https://demo2.themewarrior.com/hospitalplus/wp-content/uploads/sites/22/2015/01/pic-4-280x215.jpg"
    },
    {
        "id": 7,
        "title": "Got no reason to...",
        "description": "Now, the world don't move to the beat of just one drum, what might...",
        "image": "https://demo2.themewarrior.com/hospitalplus/wp-content/uploads/sites/22/2015/01/221-280x215.jpg"
    },
    {
        "id": 8,
        "title": "Come and knock on...",
        "description": "There's a holdout in the Bronx, Brooklyn's broken out in fights. There's a traffic...",
        "image": "https://demo2.themewarrior.com/hospitalplus/wp-content/uploads/sites/22/2015/01/gallery-41-670x500-280x215.jpg"
    }
]